hypermodern_pypras/__init__.py
hypermodern_pypras/console.py
hypermodern_pypras/wikipedia.py
hypermodern_pypras-0.1.0.dist-info/entry_points.txt
hypermodern_pypras-0.1.0.dist-info/LICENSE
hypermodern_pypras-0.1.0.dist-info/WHEEL
hypermodern_pypras-0.1.0.dist-info/METADATA
hypermodern_pypras-0.1.0.dist-info/RECORD
