Metadata-Version: 2.1
Name: hypermodern-pypras
Version: 0.1.0
Summary: The hypermodern Python Pras' project
Home-page: https://gitlab.com/prasetiyohadi/hypermodern-pypras
License: MIT
Keywords: hypermodern
Author: Prasetiyo Hadi Purwoko
Author-email: pras@deuterion.net
Requires-Python: >=3.7,<4.0
Classifier: License :: OSI Approved :: MIT License
Classifier: Programming Language :: Python :: 3
Classifier: Programming Language :: Python :: 3.7
Classifier: Programming Language :: Python :: 3.8
Requires-Dist: click (>=7.1.2,<8.0.0)
Requires-Dist: desert (>=2020.1.6,<2021.0.0)
Requires-Dist: marshmallow (>=3.6.1,<4.0.0)
Requires-Dist: requests (>=2.23.0,<3.0.0)
Project-URL: Repository, https://gitlab.com/prasetiyohadi/hypermodern-pypras
